Workbook

Sheet Dashboard
A1: VALIOUX · MANAGEMENT-DASHBOARD
B4: Spieler & Staff im Roster | C4: =COUNTA(Roster!B5:B44) | E4: Sponsoring zugesagt | F4: =Sponsoren!E47
B5: Gehaltskosten / Monat | C5: =Roster!J46 | E5: Sponsoren-Pipeline (gewichtet) | F5: =Sponsoren!G46
B6: Personalkosten / Jahr | C6: =Roster!M46 | E6: Investorengelder eingezahlt | F6: =Investoren!E26
B7: Verträge laufen aus (< 90 Tage) | C7: =COUNTIF(Roster!O5:O44,"läuft aus") | E7: Preisgelder Org-Anteil | F7: ='Turniere & Preisgeld'!G66
B8: Abgelaufene Verträge | C8: =COUNTIF(Roster!O5:O44,"abgelaufen") | E8: Jahresergebnis (Budget) | F8: ='Budget & Cashflow'!N27
B13: Tabs: Roster · Preisgeld-Split · Budget & Cashflow · Gründungskosten · Sponsoren · Investoren · Verträge · Turniere · Equipment · Tryouts · Content-Kalender · Reisekosten

Sheet Roster
A1: VALIOUX · Roster & Gehälter
A2: Gelb = Eingabe · Grau = Formel (nicht überschreiben)
A4: # | B4: Handle | C4: Name | D4: Rolle | E4: Team | F4: Land | G4: Alter | H4: Vertrag ab | I4: Vertrag bis | J4: Grundgehalt / Monat | K4: Bonus / Jahr | L4: Preisgeld-Anteil | M4: Kosten / Jahr | N4: Tage bis Ablauf | O4: Status | P4: Kündigungsfrist | Q4: Buyout € | R4: Discord / X
A5: =IF(B5="","",ROW()-4) | B5: BeispielPro1 | C5: Max Mustermann | D5: Fragger | E5: Pro | F5: DE | G5: 19 | H5: 46023 | I5: 46387 | J5: 2500 | K5: 3000 | L5: 0.25 | M5: =IF(B5="","",J5*12+K5) | N5: =IF(I5="","",I5-TODAY()) | O5: =IF(I5="","",IF(N5<0,"abgelaufen",IF(N5<90,"läuft aus","aktiv"))) | P5: 3 Monate | Q5: 15000 | R5: @bsp1
A6: =IF(B6="","",ROW()-4) | B6: BeispielPro2 | C6: Erika Beispiel | D6: IGL | E6: Pro | F6: DE | G6: 21 | H6: 46023 | I6: 46568 | J6: 3000 | K6: 5000 | L6: 0.3 | M6: =IF(B6="","",J6*12+K6) | N6: =IF(I6="","",I6-TODAY()) | O6: =IF(I6="","",IF(N6<0,"abgelaufen",IF(N6<90,"läuft aus","aktiv"))) | P6: 3 Monate | Q6: 25000 | R6: @bsp2
A7: =IF(B7="","",ROW()-4) | B7: BeispielAcad | C7: Tim Talent | D7: Talent | E7: Academy | F7: DE | G7: 16 | H7: 46174 | I7: 46387 | J7: 400 | K7: 0 | L7: 0.1 | M7: =IF(B7="","",J7*12+K7) | N7: =IF(I7="","",I7-TODAY()) | O7: =IF(I7="","",IF(N7<0,"abgelaufen",IF(N7<90,"läuft aus","aktiv"))) | P7: 1 Monat | Q7: 0 | R7: @bsp3
A8: =IF(B8="","",ROW()-4) | M8: =IF(B8="","",J8*12+K8) | N8: =IF(I8="","",I8-TODAY()) | O8: =IF(I8="","",IF(N8<0,"abgelaufen",IF(N8<90,"läuft aus","aktiv")))
A9: =IF(B9="","",ROW()-4) | M9: =IF(B9="","",J9*12+K9) | N9: =IF(I9="","",I9-TODAY()) | O9: =IF(I9="","",IF(N9<0,"abgelaufen",IF(N9<90,"läuft aus","aktiv")))
A10: =IF(B10="","",ROW()-4) | M10: =IF(B10="","",J10*12+K10) | N10: =IF(I10="","",I10-TODAY()) | O10: =IF(I10="","",IF(N10<0,"abgelaufen",IF(N10<90,"läuft aus","aktiv")))
A11: =IF(B11="","",ROW()-4) | M11: =IF(B11="","",J11*12+K11) | N11: =IF(I11="","",I11-TODAY()) | O11: =IF(I11="","",IF(N11<0,"abgelaufen",IF(N11<90,"läuft aus","aktiv")))
A12: =IF(B12="","",ROW()-4) | M12: =IF(B12="","",J12*12+K12) | N12: =IF(I12="","",I12-TODAY()) | O12: =IF(I12="","",IF(N12<0,"abgelaufen",IF(N12<90,"läuft aus","aktiv")))
A13: =IF(B13="","",ROW()-4) | M13: =IF(B13="","",J13*12+K13) | N13: =IF(I13="","",I13-TODAY()) | O13: =IF(I13="","",IF(N13<0,"abgelaufen",IF(N13<90,"läuft aus","aktiv")))
A14: =IF(B14="","",ROW()-4) | M14: =IF(B14="","",J14*12+K14) | N14: =IF(I14="","",I14-TODAY()) | O14: =IF(I14="","",IF(N14<0,"abgelaufen",IF(N14<90,"läuft aus","aktiv")))
A15: =IF(B15="","",ROW()-4) | M15: =IF(B15="","",J15*12+K15) | N15: =IF(I15="","",I15-TODAY()) | O15: =IF(I15="","",IF(N15<0,"abgelaufen",IF(N15<90,"läuft aus","aktiv")))
A16: =IF(B16="","",ROW()-4) | M16: =IF(B16="","",J16*12+K16) | N16: =IF(I16="","",I16-TODAY()) | O16: =IF(I16="","",IF(N16<0,"abgelaufen",IF(N16<90,"läuft aus","aktiv")))
A17: =IF(B17="","",ROW()-4) | M17: =IF(B17="","",J17*12+K17) | N17: =IF(I17="","",I17-TODAY()) | O17: =IF(I17="","",IF(N17<0,"abgelaufen",IF(N17<90,"läuft aus","aktiv")))
A18: =IF(B18="","",ROW()-4) | M18: =IF(B18="","",J18*12+K18) | N18: =IF(I18="","",I18-TODAY()) | O18: =IF(I18="","",IF(N18<0,"abgelaufen",IF(N18<90,"läuft aus","aktiv")))
A19: =IF(B19="","",ROW()-4) | M19: =IF(B19="","",J19*12+K19) | N19: =IF(I19="","",I19-TODAY()) | O19: =IF(I19="","",IF(N19<0,"abgelaufen",IF(N19<90,"läuft aus","aktiv")))
... A44: =IF(B44="","",ROW()-4) | M44: =IF(B44="","",J44*12+K44) | N44: =IF(I44="","",I44-TODAY()) | O44: =IF(I44="","",IF(N44<0,"abgelaufen",IF(N44<90,"läuft aus","aktiv")))
I46: Summe | J46: =SUM(J5:J44) | K46: =SUM(K5:K44) | M46: =SUM(M5:M44)

Sheet Preisgeld-Split
A1: VALIOUX · Preisgeld- & Bonus-Rechner
A2: Gelb = Eingabe · Grau = Formel (nicht überschreiben)
A4: Turnier-Preisgeld gesamt (Team) | B4: 0
A5: Anteil Organisation | B5: 0.3
A6: Anteil Spieler (gesamt) | B6: =1-B5
A7: Betrag Organisation | B7: =B4*B5
A8: Betrag Spieler (gesamt) | B8: =B4*B6
A10: Spieler | B10: Gewichtung | C10: Anteil % | D10: Auszahlung brutto | E10: Notiz
C11: =IF(B11="","",B11/SUM($B$11:$B$18)) | D11: =IF(B11="","",C11*$B$8)
C12: =IF(B12="","",B12/SUM($B$11:$B$18)) | D12: =IF(B12="","",C12*$B$8)
C13: =IF(B13="","",B13/SUM($B$11:$B$18)) | D13: =IF(B13="","",C13*$B$8)
C14: =IF(B14="","",B14/SUM($B$11:$B$18)) | D14: =IF(B14="","",C14*$B$8)
C15: =IF(B15="","",B15/SUM($B$11:$B$18)) | D15: =IF(B15="","",C15*$B$8)
C16: =IF(B16="","",B16/SUM($B$11:$B$18)) | D16: =IF(B16="","",C16*$B$8)
C17: =IF(B17="","",B17/SUM($B$11:$B$18)) | D17: =IF(B17="","",C17*$B$8)
C18: =IF(B18="","",B18/SUM($B$11:$B$18)) | D18: =IF(B18="","",C18*$B$8)
A20: Hinweis: Gewichtung z. B. 1 = gleichmäßig. Steuern/Sozialabgaben separat prüfen (Steuerberater).

Sheet Budget & Cashflow
A1: VALIOUX · Jahresbudget & Cashflow
A2: Gelb = Eingabe · Grau = Formel (nicht überschreiben)
A3: Startkapital (Kontostand) | B3: 0
A5: Kategorie | B5: Jan | C5: Feb | D5: Mär | E5: Apr | F5: Mai | G5: Jun | H5: Jul | I5: Aug | J5: Sep | K5: Okt | L5: Nov | M5: Dez | N5: Summe
A6: EINNAHMEN
A7: Sponsoring | N7: =SUM(B7:M7)
A8: Preisgelder | N8: =SUM(B8:M8)
A9: Merch / Shop | N9: =SUM(B9:M9)
A10: Content / Werbeeinnahmen | N10: =SUM(B10:M10)
A11: Investorengelder | N11: =SUM(B11:M11)
A12: Sonstiges | N12: =SUM(B12:M12)
A13: Summe Einnahmen | B13: =SUM(B7:B12) | C13: =SUM(C7:C12) | D13: =SUM(D7:D12) | E13: =SUM(E7:E12) | F13: =SUM(F7:F12) | G13: =SUM(G7:G12) | H13: =SUM(H7:H12) | I13: =SUM(I7:I12) | ... N13: =SUM(N7:N12)
A15: AUSGABEN
A16: Spielergehälter (aus Roster) | B16: =Roster!$J$46 | C16: =Roster!$J$46 | D16: =Roster!$J$46 | E16: =Roster!$J$46 | F16: =Roster!$J$46 | G16: =Roster!$J$46 | H16: =Roster!$J$46 | I16: =Roster!$J$46 | ... M16: =Roster!$J$46 | N16: =SUM(B16:M16)
A17: Staff / Coaches | N17: =SUM(B17:M17)
A18: Bootcamp & Reisen | N18: =SUM(B18:M18)
A19: Equipment & Hardware | N19: =SUM(B19:M19)
A20: Marketing & Content-Produktion | N20: =SUM(B20:M20)
A21: Software & Tools | N21: =SUM(B21:M21)
A22: Recht, Steuer, Versicherung | N22: =SUM(B22:M22)
A23: Turniergebühren / Slots | N23: =SUM(B23:M23)
A24: Sonstiges | N24: =SUM(B24:M24)
A25: Summe Ausgaben | B25: =SUM(B16:B24) | C25: =SUM(C16:C24) | D25: =SUM(D16:D24) | E25: =SUM(E16:E24) | F25: =SUM(F16:F24) | G25: =SUM(G16:G24) | H25: =SUM(H16:H24) | I25: =SUM(I16:I24) | ... N25: =SUM(N16:N24)
A27: Ergebnis (Monat) | B27: =B13-B25 | C27: =C13-C25 | D27: =D13-D25 | E27: =E13-E25 | F27: =F13-F25 | G27: =G13-G25 | H27: =H13-H25 | I27: =I13-I25 | ... N27: =N13-N25
A28: Kontostand kumuliert | B28: =$B$3+SUM($B$27:B27) | C28: =$B$3+SUM($B$27:C27) | D28: =$B$3+SUM($B$27:D27) | E28: =$B$3+SUM($B$27:E27) | F28: =$B$3+SUM($B$27:F27) | G28: =$B$3+SUM($B$27:G27) | H28: =$B$3+SUM($B$27:H27) | I28: =$B$3+SUM($B$27:I27) | ... M28: =$B$3+SUM($B$27:M27)

Sheet Gründungskosten
A1: VALIOUX · Einmalige Gründungskosten
A2: Gelb = Eingabe · Grau = Formel (nicht überschreiben)
A4: Posten | B4: Geplant € | C4: Ist € | D4: Status | E4: Hinweis
A5: Rechtsform-Gründung (Notar, Handelsregister) | E5: Je nach Rechtsform/Land; Beratung einholen
A6: Rechtsberatung Verträge (Spieler, Sponsor, Investor) | E6: Vorlagen prüfen lassen
A7: Markenanmeldung (Wort-/Bildmarke) | E7: Klassen 9, 25, 35, 41; Recherche vorab
A8: Domain(s) & Hosting | E8: Hauptdomain + Schutzdomains
A9: Logo/Branding/Design (extern) | E9: Falls nicht selbst erstellt
A10: Trikot-Erstausstattung | E10: Design, Muster, Erstserie, Größen
A11: Hardware-Erstausstattung | E11: PCs, Monitore, Peripherie
A12: Versicherungen (Haftpflicht, Equipment, Unfall) | E12: Angebote vergleichen
A13: Steuerberater / Buchhaltung Setup
A14: Bankkonto, Zahlungsanbieter
A15: Software (Notion, Discord Bots, Adobe, OBS-Tools)
A16: Website Betrieb / Tools
A17: Launch-Marketing / Content-Paket
A18: Reserve (10–20 %)
A20: Summe | B20: =SUM(B5:B18) | C20: =SUM(C5:C18)

Sheet Sponsoren
A1: VALIOUX · Sponsoren-Pipeline
A2: Gelb = Eingabe · Grau = Formel (nicht überschreiben)
A4: Firma | B4: Ansprechpartner | C4: Kontakt | D4: Phase | E4: Deal-Wert € | F4: Wahrscheinlichkeit | G4: Gewichtet € | H4: Nächster Schritt am | I4: Notiz
G5: =IF(E5="","",E5*F5)
G6: =IF(E6="","",E6*F6)
G7: =IF(E7="","",E7*F7)
G8: =IF(E8="","",E8*F8)
G9: =IF(E9="","",E9*F9)
G10: =IF(E10="","",E10*F10)
G11: =IF(E11="","",E11*F11)
G12: =IF(E12="","",E12*F12)
G13: =IF(E13="","",E13*F13)
G14: =IF(E14="","",E14*F14)
G15: =IF(E15="","",E15*F15)
G16: =IF(E16="","",E16*F16)
... G44: =IF(E44="","",E44*F44)
A46: Pipeline gesamt | E46: =SUM(E5:E44) | G46: =SUM(G5:G44)
A47: Zugesagt | E47: =SUMIF(D5:D44,"Zugesagt",E5:E44)

Sheet Investoren
A1: VALIOUX · Investoren-Tracker
A2: Gelb = Eingabe · Grau = Formel (nicht überschreiben)
A4: Investor | B4: Ansprechpartner | C4: Kontakt | D4: Phase | E4: Summe € | F4: Anteil % | G4: Pre-Money € | H4: Nächster Schritt am | I4: Notiz
A26: Eingezahlt gesamt | E26: =SUMIF(D5:D24,"Eingezahlt",E5:E24)
A27: Verbleibende Anteile Gründer | F27: =1-SUMIF(D5:D24,"Eingezahlt",F5:F24)

Sheet Verträge
A1: VALIOUX · Vertrags-Tracker mit Ablauf-Warnung
A2: Gelb = Eingabe · Grau = Formel (nicht überschreiben)
A4: Nr. | B4: Partner | C4: Typ | D4: Beginn | E4: Ende | F4: Tage bis Ablauf | G4: Warnung | H4: Wert € | I4: Dokument-Link / Notiz
F5: =IF(E5="","",E5-TODAY()) | G5: =IF(E5="","",IF(F5<0,"ABGELAUFEN",IF(F5<=90,"bald fällig","ok")))
F6: =IF(E6="","",E6-TODAY()) | G6: =IF(E6="","",IF(F6<0,"ABGELAUFEN",IF(F6<=90,"bald fällig","ok")))
F7: =IF(E7="","",E7-TODAY()) | G7: =IF(E7="","",IF(F7<0,"ABGELAUFEN",IF(F7<=90,"bald fällig","ok")))
F8: =IF(E8="","",E8-TODAY()) | G8: =IF(E8="","",IF(F8<0,"ABGELAUFEN",IF(F8<=90,"bald fällig","ok")))
F9: =IF(E9="","",E9-TODAY()) | G9: =IF(E9="","",IF(F9<0,"ABGELAUFEN",IF(F9<=90,"bald fällig","ok")))
F10: =IF(E10="","",E10-TODAY()) | G10: =IF(E10="","",IF(F10<0,"ABGELAUFEN",IF(F10<=90,"bald fällig","ok")))
F11: =IF(E11="","",E11-TODAY()) | G11: =IF(E11="","",IF(F11<0,"ABGELAUFEN",IF(F11<=90,"bald fällig","ok")))
F12: =IF(E12="","",E12-TODAY()) | G12: =IF(E12="","",IF(F12<0,"ABGELAUFEN",IF(F12<=90,"bald fällig","ok")))
F13: =IF(E13="","",E13-TODAY()) | G13: =IF(E13="","",IF(F13<0,"ABGELAUFEN",IF(F13<=90,"bald fällig","ok")))
F14: =IF(E14="","",E14-TODAY()) | G14: =IF(E14="","",IF(F14<0,"ABGELAUFEN",IF(F14<=90,"bald fällig","ok")))
F15: =IF(E15="","",E15-TODAY()) | G15: =IF(E15="","",IF(F15<0,"ABGELAUFEN",IF(F15<=90,"bald fällig","ok")))
F16: =IF(E16="","",E16-TODAY()) | G16: =IF(E16="","",IF(F16<0,"ABGELAUFEN",IF(F16<=90,"bald fällig","ok")))
... F54: =IF(E54="","",E54-TODAY()) | G54: =IF(E54="","",IF(F54<0,"ABGELAUFEN",IF(F54<=90,"bald fällig","ok")))

Sheet Turniere & Preisgeld
A1: VALIOUX · Turnier- & Preisgeld-Tracker
A2: Gelb = Eingabe · Grau = Formel (nicht überschreiben)
A4: Datum | B4: Turnier | C4: Team | D4: Platzierung | E4: Preisgeld € | F4: Org-Anteil % | G4: Org-Betrag € | H4: Notiz
G5: =IF(E5="","",E5*F5)
G6: =IF(E6="","",E6*F6)
G7: =IF(E7="","",E7*F7)
G8: =IF(E8="","",E8*F8)
G9: =IF(E9="","",E9*F9)
G10: =IF(E10="","",E10*F10)
G11: =IF(E11="","",E11*F11)
G12: =IF(E12="","",E12*F12)
G13: =IF(E13="","",E13*F13)
G14: =IF(E14="","",E14*F14)
G15: =IF(E15="","",E15*F15)
G16: =IF(E16="","",E16*F16)
... G64: =IF(E64="","",E64*F64)
D66: Summe | E66: =SUM(E5:E64) | G66: =SUM(G5:G64)

Sheet Equipment
A1: VALIOUX · Equipment-Inventar
A2: Gelb = Eingabe · Grau = Formel (nicht überschreiben)
A4: Nr. | B4: Gerät | C4: Hersteller/Modell | D4: Seriennummer | E4: Kaufdatum | F4: Wert € | G4: Ausgegeben an | H4: Zustand | I4: Rückgabe bis

Sheet Tryouts
A1: VALIOUX · Scouting & Tryout-Board
A2: Gelb = Eingabe · Grau = Formel (nicht überschreiben)
A4: Kandidat | B4: Alter | C4: Kontakt | D4: Mechanik | E4: Game Sense | F4: Komm. | G4: Teamfit | H4: Coachability | I4: Konstanz | J4: Content | K4: Ø Score | L4: Status | M4: Notiz
K5: =IF(COUNT(D5:J5)=0,"",ROUND(AVERAGE(D5:J5),2))
K6: =IF(COUNT(D6:J6)=0,"",ROUND(AVERAGE(D6:J6),2))
K7: =IF(COUNT(D7:J7)=0,"",ROUND(AVERAGE(D7:J7),2))
K8: =IF(COUNT(D8:J8)=0,"",ROUND(AVERAGE(D8:J8),2))
K9: =IF(COUNT(D9:J9)=0,"",ROUND(AVERAGE(D9:J9),2))
K10: =IF(COUNT(D10:J10)=0,"",ROUND(AVERAGE(D10:J10),2))
K11: =IF(COUNT(D11:J11)=0,"",ROUND(AVERAGE(D11:J11),2))
K12: =IF(COUNT(D12:J12)=0,"",ROUND(AVERAGE(D12:J12),2))
K13: =IF(COUNT(D13:J13)=0,"",ROUND(AVERAGE(D13:J13),2))
K14: =IF(COUNT(D14:J14)=0,"",ROUND(AVERAGE(D14:J14),2))
K15: =IF(COUNT(D15:J15)=0,"",ROUND(AVERAGE(D15:J15),2))
K16: =IF(COUNT(D16:J16)=0,"",ROUND(AVERAGE(D16:J16),2))
... K54: =IF(COUNT(D54:J54)=0,"",ROUND(AVERAGE(D54:J54),2))

Sheet Content-Kalender
A1: VALIOUX · Content- & Post-Kalender
A2: Gelb = Eingabe · Grau = Formel (nicht überschreiben)
A4: Datum | B4: Zeit | C4: Kanal | D4: Inhalt / Idee | E4: Format | F4: Verantwortlich | G4: Status

Sheet Reisekosten
A1: VALIOUX · Reise- & Bootcamp-Kosten
A2: Gelb = Eingabe · Grau = Formel (nicht überschreiben)
A4: Datum | B4: Event / Ziel | C4: Person | D4: Reise € | E4: Hotel € | F4: Verpflegung € | G4: Sonstiges € | H4: Summe €
H5: =IF(COUNT(D5:G5)=0,"",SUM(D5:G5))
H6: =IF(COUNT(D6:G6)=0,"",SUM(D6:G6))
H7: =IF(COUNT(D7:G7)=0,"",SUM(D7:G7))
H8: =IF(COUNT(D8:G8)=0,"",SUM(D8:G8))
H9: =IF(COUNT(D9:G9)=0,"",SUM(D9:G9))
H10: =IF(COUNT(D10:G10)=0,"",SUM(D10:G10))
H11: =IF(COUNT(D11:G11)=0,"",SUM(D11:G11))
H12: =IF(COUNT(D12:G12)=0,"",SUM(D12:G12))
H13: =IF(COUNT(D13:G13)=0,"",SUM(D13:G13))
H14: =IF(COUNT(D14:G14)=0,"",SUM(D14:G14))
H15: =IF(COUNT(D15:G15)=0,"",SUM(D15:G15))
H16: =IF(COUNT(D16:G16)=0,"",SUM(D16:G16))
... H54: =IF(COUNT(D54:G54)=0,"",SUM(D54:G54))
G56: Gesamt | H56: =SUM(H5:H54)
